{
  "_class": "symbolInstance",
  "booleanOperation": 0,
  "clippingMaskMode": 0,
  "do_objectID": "99BCE980-79F2-4755-BF9A-DB352012442B",
  "exportOptions": {
    "_class": "exportOptions",
    "do_objectID": "A9E5E046-8804-472A-9A14-FD0B6AFD1DA0",
    "exportFormats": [
    ],
    "includedLayerIds": [
    ],
    "layerOptions": 0,
    "shouldTrim": false
  },
  "frame": {
    "_class": "rect",
    "constrainProportions": false,
    "do_objectID": "120978D8-F7AF-4040-BC85-8BEDFF0EC88F",
    "height": 1,
    "width": 766,
    "x": 0,
    "y": 179
  },
  "hasClippingMask": false,
  "horizontalSpacing": 0,
  "isFixedToViewport": false,
  "isFlippedHorizontal": false,
  "isFlippedVertical": false,
  "isLocked": false,
  "isVisible": true,
  "layerListExpandedType": 0,
  "name": "separator",
  "nameIsFixed": false,
  "overrideValues": [
  ],
  "resizingConstraint": 63,
  "resizingType": 0,
  "rotation": 0,
  "scale": 1,
  "shouldBreakMaskChain": false,
  "style": {
    "_class": "style",
    "do_objectID": "3ADF6884-3EFC-451B-9CDB-6CADE051049B",
    "endMarkerType": 0,
    "miterLimit": 10,
    "startMarkerType": 0,
    "windingRule": 1
  },
  "symbolID": "09919A1C-E41E-4C22-8D39-F6049D5799D0",
  "verticalSpacing": 0
}