{
  "_class": "symbolInstance",
  "booleanOperation": 0,
  "clippingMaskMode": 0,
  "do_objectID": "381D99EC-A5F4-4614-BE0B-4463CD8F8705",
  "exportOptions": {
    "_class": "exportOptions",
    "do_objectID": "BDEB9533-98C1-4193-87CB-573520824A87",
    "exportFormats": [
    ],
    "includedLayerIds": [
    ],
    "layerOptions": 0,
    "shouldTrim": false
  },
  "frame": {
    "_class": "rect",
    "constrainProportions": false,
    "do_objectID": "9D822842-A8ED-499E-833E-7422DD78492E",
    "height": 1,
    "width": 352,
    "x": 0,
    "y": 453
  },
  "hasClippingMask": false,
  "horizontalSpacing": 0,
  "isFixedToViewport": false,
  "isFlippedHorizontal": false,
  "isFlippedVertical": false,
  "isLocked": false,
  "isVisible": true,
  "layerListExpandedType": 0,
  "name": "separator copy 3",
  "nameIsFixed": false,
  "overrideValues": [
  ],
  "resizingConstraint": 63,
  "resizingType": 0,
  "rotation": 0,
  "scale": 1,
  "shouldBreakMaskChain": false,
  "style": {
    "_class": "style",
    "do_objectID": "0BF5FAFB-C270-437B-8763-49EC615CEAC1",
    "endMarkerType": 0,
    "miterLimit": 10,
    "startMarkerType": 0,
    "windingRule": 1
  },
  "symbolID": "09919A1C-E41E-4C22-8D39-F6049D5799D0",
  "verticalSpacing": 0
}