{
  "_class": "symbolInstance",
  "booleanOperation": 0,
  "clippingMaskMode": 0,
  "do_objectID": "279545B2-85B4-4C26-95A2-360F91906ED8",
  "exportOptions": {
    "_class": "exportOptions",
    "do_objectID": "A4EF7493-BCC5-4146-B7E5-CADC658FAC9C",
    "exportFormats": [
    ],
    "includedLayerIds": [
    ],
    "layerOptions": 0,
    "shouldTrim": false
  },
  "frame": {
    "_class": "rect",
    "constrainProportions": false,
    "do_objectID": "8A006942-2845-43BE-A1CB-56102B4B5CC6",
    "height": 110,
    "width": 175,
    "x": 0,
    "y": 125
  },
  "hasClippingMask": false,
  "horizontalSpacing": 0,
  "isFixedToViewport": false,
  "isFlippedHorizontal": false,
  "isFlippedVertical": false,
  "isLocked": false,
  "isVisible": true,
  "layerListExpandedType": 0,
  "name": "container/placeholder/grey-fill copy",
  "nameIsFixed": false,
  "overrideValues": [
  ],
  "resizingConstraint": 63,
  "resizingType": 0,
  "rotation": 0,
  "scale": 1,
  "shouldBreakMaskChain": false,
  "style": {
    "_class": "style",
    "do_objectID": "BF4F2DDC-8C89-4EB4-BBB6-23D2F8999B6B",
    "endMarkerType": 0,
    "miterLimit": 10,
    "startMarkerType": 0,
    "windingRule": 1
  },
  "symbolID": "4017C6DC-7C41-4BBC-B96D-D1724E3DCF1C",
  "verticalSpacing": 0
}