{
  "_class": "symbolInstance",
  "booleanOperation": 0,
  "clippingMaskMode": 0,
  "do_objectID": "94CE7DC3-A7CF-4CA1-9F77-7C77617E5A77",
  "exportOptions": {
    "_class": "exportOptions",
    "do_objectID": "9E509097-2DAF-4815-9EDB-06616F2E69D4",
    "exportFormats": [
    ],
    "includedLayerIds": [
    ],
    "layerOptions": 0,
    "shouldTrim": false
  },
  "frame": {
    "_class": "rect",
    "constrainProportions": false,
    "do_objectID": "33A4F528-E4EC-4BD5-AA16-092A6900EA23",
    "height": 40,
    "width": 512,
    "x": 244,
    "y": 174
  },
  "hasClippingMask": false,
  "horizontalSpacing": 0,
  "isFixedToViewport": false,
  "isFlippedHorizontal": false,
  "isFlippedVertical": false,
  "isLocked": false,
  "isVisible": true,
  "layerListExpandedType": 0,
  "name": "Page Title",
  "nameIsFixed": false,
  "overrideValues": [
    {
      "_class": "overrideValue",
      "do_objectID": "A0EBDB20-D9E9-4931-9B1B-0A468F73C651",
      "overrideName": "872A280D-A0DF-4B79-B71C-97CAC8CEA7FB_stringValue",
      "value": "Board of Directors"
    }
  ],
  "resizingConstraint": 47,
  "resizingType": 0,
  "rotation": 0,
  "scale": 1,
  "shouldBreakMaskChain": false,
  "style": {
    "_class": "style",
    "do_objectID": "62A55D43-2DB6-4088-823A-07129A5B80D9",
    "endMarkerType": 0,
    "miterLimit": 10,
    "startMarkerType": 0,
    "windingRule": 1
  },
  "symbolID": "858025DD-D9C6-479A-81C8-D53FFF21C3C1",
  "verticalSpacing": 0
}