{
  "_class": "symbolInstance",
  "booleanOperation": 0,
  "clippingMaskMode": 0,
  "do_objectID": "EE2EDA4C-1AD9-43DC-8910-ECE68788AB17",
  "exportOptions": {
    "_class": "exportOptions",
    "do_objectID": "90797C49-FCBB-4BAB-84FA-C136889BB04B",
    "exportFormats": [
    ],
    "includedLayerIds": [
    ],
    "layerOptions": 0,
    "shouldTrim": false
  },
  "frame": {
    "_class": "rect",
    "constrainProportions": false,
    "do_objectID": "6C528AE4-0D9D-474A-81B3-54A42E4DA2F7",
    "height": 40,
    "width": 150,
    "x": 5,
    "y": 782
  },
  "hasClippingMask": false,
  "horizontalSpacing": 0,
  "isFixedToViewport": false,
  "isFlippedHorizontal": false,
  "isFlippedVertical": false,
  "isLocked": false,
  "isVisible": false,
  "layerListExpandedType": 0,
  "name": "button reg copy",
  "nameIsFixed": false,
  "overrideValues": [
    {
      "_class": "overrideValue",
      "do_objectID": "2AC89557-E3EC-42A7-8DD8-82975ECA1EAE",
      "overrideName": "CE4D5B2B-512C-43F5-B05C-EB89BB929075_stringValue",
      "value": "Renew"
    }
  ],
  "resizingConstraint": 63,
  "resizingType": 0,
  "rotation": 0,
  "scale": 1,
  "shouldBreakMaskChain": false,
  "style": {
    "_class": "style",
    "do_objectID": "27AAB0B9-139A-4F1B-BFA4-9C408CA192F9",
    "endMarkerType": 0,
    "miterLimit": 10,
    "startMarkerType": 0,
    "windingRule": 1
  },
  "symbolID": "E626A3BB-C3C0-4686-BE42-48377058C0E8",
  "verticalSpacing": 0
}