{
  "_class": "symbolInstance",
  "booleanOperation": 0,
  "clippingMaskMode": 0,
  "do_objectID": "A796C9DA-AE6E-4475-BD18-A0C08C9CE192",
  "exportOptions": {
    "_class": "exportOptions",
    "do_objectID": "83C0150C-464C-4615-A33D-F08D35F2AF50",
    "exportFormats": [
    ],
    "includedLayerIds": [
    ],
    "layerOptions": 0,
    "shouldTrim": false
  },
  "frame": {
    "_class": "rect",
    "constrainProportions": false,
    "do_objectID": "A41E8217-E92C-4A8B-8291-96D66DA8537D",
    "height": 200,
    "width": 408,
    "x": 308,
    "y": 150
  },
  "hasClippingMask": false,
  "horizontalSpacing": 0,
  "isFixedToViewport": false,
  "isFlippedHorizontal": false,
  "isFlippedVertical": false,
  "isLocked": false,
  "isVisible": true,
  "layerListExpandedType": 0,
  "name": "container/placeholder/grey-fill",
  "nameIsFixed": false,
  "overrideValues": [
  ],
  "resizingConstraint": 63,
  "resizingType": 0,
  "rotation": 0,
  "scale": 1,
  "shouldBreakMaskChain": false,
  "style": {
    "_class": "style",
    "do_objectID": "0CAF49E8-F557-435B-BB96-8B0E25817743",
    "endMarkerType": 0,
    "miterLimit": 10,
    "startMarkerType": 0,
    "windingRule": 1
  },
  "symbolID": "4017C6DC-7C41-4BBC-B96D-D1724E3DCF1C",
  "verticalSpacing": 0
}