{
  "_class": "symbolInstance",
  "booleanOperation": 0,
  "clippingMaskMode": 0,
  "do_objectID": "B573DCF8-7AF5-4749-9F16-38B8982486D7",
  "exportOptions": {
    "_class": "exportOptions",
    "do_objectID": "9718E06C-978B-4A25-989C-137884385AED",
    "exportFormats": [
    ],
    "includedLayerIds": [
    ],
    "layerOptions": 0,
    "shouldTrim": false
  },
  "frame": {
    "_class": "rect",
    "constrainProportions": false,
    "do_objectID": "9C814599-F726-4E51-AA69-25D7B8C47F0D",
    "height": 25,
    "width": 40,
    "x": 91,
    "y": 0
  },
  "hasClippingMask": false,
  "horizontalSpacing": 0,
  "isFixedToViewport": false,
  "isFlippedHorizontal": false,
  "isFlippedVertical": false,
  "isLocked": false,
  "isVisible": true,
  "layerListExpandedType": 0,
  "name": "container/placeholder/grey-fill",
  "nameIsFixed": false,
  "overrideValues": [
  ],
  "resizingConstraint": 63,
  "resizingType": 0,
  "rotation": 0,
  "scale": 1,
  "shouldBreakMaskChain": false,
  "style": {
    "_class": "style",
    "do_objectID": "AAC15941-C59C-4B3D-BF7B-BC7DB48E7A9E",
    "endMarkerType": 0,
    "miterLimit": 10,
    "startMarkerType": 0,
    "windingRule": 1
  },
  "symbolID": "4017C6DC-7C41-4BBC-B96D-D1724E3DCF1C",
  "verticalSpacing": 0
}