{
  "_class": "text",
  "attributedString": {
    "_class": "attributedString",
    "attributes": [
      {
        "_class": "stringAttribute",
        "attributes": {
          "MSAttributedStringColorAttribute": {
            "_class": "color",
            "alpha": 1,
            "blue": 0.1882352941,
            "green": 0.1843137255,
            "red": 0.1764705882
          },
          "MSAttributedStringFontAttribute": {
            "_class": "fontDescriptor",
            "attributes": {
              "name": "Roboto-Regular",
              "size": 14
            }
          },
          "kerning": 0,
          "paragraphStyle": {
            "_class": "paragraphStyle",
            "alignment": 2,
            "allowsDefaultTighteningForTruncation": 0,
            "maximumLineHeight": 20,
            "minimumLineHeight": 20,
            "paragraphSpacing": 5
          }
        },
        "length": 50,
        "location": 0
      }
    ],
    "string": "Check Terms and Conditions\nfor Platinum Membership"
  },
  "automaticallyDrawOnUnderlyingPath": false,
  "booleanOperation": 0,
  "clippingMaskMode": 0,
  "do_objectID": "E9D4FF50-CC39-42A9-AB18-E119C55CD204",
  "dontSynchroniseWithSymbol": false,
  "exportOptions": {
    "_class": "exportOptions",
    "do_objectID": "B78A498B-7AD4-47F1-8586-55B1134FF58F",
    "exportFormats": [
    ],
    "includedLayerIds": [
    ],
    "layerOptions": 0,
    "shouldTrim": false
  },
  "frame": {
    "_class": "rect",
    "constrainProportions": false,
    "do_objectID": "6F9C61A1-E342-437D-B66C-15162D05F3FE",
    "height": 45,
    "width": 181,
    "x": 639,
    "y": 309
  },
  "glyphBounds": "{{0, 4}, {181, 39}}",
  "hasClippingMask": false,
  "isFixedToViewport": false,
  "isFlippedHorizontal": false,
  "isFlippedVertical": false,
  "isLocked": false,
  "isVisible": true,
  "layerListExpandedType": 0,
  "lineSpacingBehaviour": 2,
  "name": "Check Terms and Cond",
  "nameIsFixed": false,
  "resizingConstraint": 47,
  "resizingType": 0,
  "rotation": 0,
  "sharedStyleID": "718E3D48-9E51-4671-834A-071E0E77D49E",
  "shouldBreakMaskChain": false,
  "style": {
    "_class": "style",
    "do_objectID": "DFF6B54F-3B66-4779-AD6F-BF4C92705208",
    "endMarkerType": 0,
    "miterLimit": 10,
    "startMarkerType": 0,
    "textStyle": {
      "_class": "textStyle",
      "do_objectID": "767AA359-3618-456A-915C-2F0E997B9EBF",
      "encodedAttributes": {
        "MSAttributedStringColorAttribute": {
          "_class": "color",
          "alpha": 1,
          "blue": 0.1882352941,
          "green": 0.1843137255,
          "red": 0.1764705882
        },
        "MSAttributedStringFontAttribute": {
          "_class": "fontDescriptor",
          "attributes": {
            "name": "Roboto-Regular",
            "size": 14
          }
        },
        "kerning": 0,
        "paragraphStyle": {
          "_class": "paragraphStyle",
          "alignment": 2,
          "allowsDefaultTighteningForTruncation": 0,
          "maximumLineHeight": 20,
          "minimumLineHeight": 20,
          "paragraphSpacing": 5
        }
      },
      "verticalAlignment": 0
    },
    "windingRule": 1
  },
  "textBehaviour": 0
}